[

	//techguns

	{
		"dimension": 0,
		"mobs":	[
			{
				"mob": "techguns:zombiepoliceman",
				"weight": 30,
				"groupcountmin": 1,
				"groupcountmax": 5
			}
		]
	},

	{
		"dimension": 0,
		"mobs":	[
			{
				"mob": "techguns:zombiesoldier",
				"weight": 30,
				"groupcountmin": 1,
				"groupcountmax": 5
			}
		]
	},

	{
		"dimension": 0,
		"mobs":	[
			{
				"mob": "techguns:zombiefarmer",
				"weight": 60,
				"groupcountmin": 1,
				"groupcountmax": 5
			}
		]
	},

	{
		"dimension": 0,
		"mobs":	[
			{
				"mob": "techguns:zombieminer",
				"weight": 60,
				"groupcountmin": 1,
				"groupcountmax": 5
			}
		]
	},

	{
		"dimension": -1,
		"mobs":	[
			{
				"mob": "techguns:zombiepigmansoldier",
				"weight": 20,
				"groupcountmin": 1,
				"groupcountmax": 3
			}
		]
	},

	{
		"dimension": -1,
		"mobs":	[
			{
				"mob": "techguns:cyberdemon",
				"weight": 10,
				"groupcountmin": 1,
				"groupcountmax": 2
			}
		]
	},

	{
		"dimension": 0,
		"mobs":	[
			{
				"mob": "techguns:skeletonsoldier",
				"weight": 30,
				"groupcountmin": 1,
				"groupcountmax": 5
			}
		]
	},

	{
		"dimension": 0,
		"mobs":	[
			{
				"mob": "techguns:psychosteve",
				"weight": 10,
				"groupcountmin": 1,
				"groupcountmax": 2
			}
		]
	},

	{
		"dimension": 0,
		"mobs":	[
			{
				"mob": "techguns:supermutantbasic",
				"weight": 15,
				"groupcountmin": 2,
				"groupcountmax": 4
			}
		]
	},

	{
		"dimension": 0,
		"mobs":	[
			{
				"mob": "techguns:supermutantheavy",
				"weight": 10,
				"groupcountmin": 1,
				"groupcountmax": 2
			}
		]
	},

	{
		"dimension": 0,
		"mobs":	[
			{
				"mob": "techguns:supermutantelite",
				"weight": 5,
				"groupcountmin": 1,
				"groupcountmax": 1
			}
		]
	},

	{
		"dimension": 0,
		"mobs":	[
			{
				"mob": "techguns:outcast",
				"weight": 10,
				"groupcountmin": 1,
				"groupcountmax": 3
			}
		]
	},
	
	//srp

	{
		"dimension": 1,
		"mobs":	[
			{
				"mob": "srparasites:warden",
				"weight": 3,
				"groupcountmin": 1,
				"groupcountmax": 1
			}
		]
	},
	{
		"dimension": [0,1],
		"mobs":	[
			{
				"mob": "srparasites:marauder",
				"weight": 2,
				"groupcountmin": 1,
				"groupcountmax": 1
			}
		]
	},
	{
		"dimension": 0,
		"mobs":	[
			{
				"mob": "srparasites:carrier_heavy",
				"weight": 9,
				"groupcountmin": 1,
				"groupcountmax": 2
			}
		]
	},
	{
		"dimension": 0,
		"mobs":	[
			{
				"mob": "srparasites:rupter",
				"weight": 9,
				"groupcountmin": 1,
				"groupcountmax": 18
			}
		]
	},
	{
		"dimension": 0,
		"mobs":	[
			{
				"mob": "srparasites:sim_human",
				"weight": 9,
				"groupcountmin": 1,
				"groupcountmax": 12
			}
		]
	}
]